pycopula/__init__.py
pycopula/archimedean_generators.py
pycopula/copula.py
pycopula/estimation.py
pycopula/example_2.py
pycopula/examples.py
pycopula/main.py
pycopula/math_misc.py
pycopula/simulation.py
pycopula/visualization.py
pycopula-0.1.5.dist-info/AUTHORS
pycopula-0.1.5.dist-info/LICENSE
pycopula-0.1.5.dist-info/METADATA
pycopula-0.1.5.dist-info/WHEEL
pycopula-0.1.5.dist-info/top_level.txt
pycopula-0.1.5.dist-info/RECORD
