Metadata-Version: 2.1
Name: pycopula
Version: 0.1.5
Summary: Python copulas library for dependency modeling
Home-page: https://github.com/MaximeJumelle/pycopula/
Author: Maxime Jumelle
Author-email: maxime@aipcloud.io
License: Apache 2
Keywords: pycopula
Platform: UNKNOWN
Requires-Dist: numpy (>=1.13.3)
Requires-Dist: scipy (>=1.0.0)
